<?xml version="1.0" encoding="utf-8" ?>
<dwsync>
<file name="borderBottomCenter.png" server="//192.168.1.2/wamp/www/busticketing/" local="129379350189036139" remote="129379350180000000" />
<file name="borderBottomLeft.png" server="//192.168.1.2/wamp/www/busticketing/" local="129379350189566170" remote="129379350180000000" />
<file name="borderBottomRight.png" server="//192.168.1.2/wamp/www/busticketing/" local="129379350189896189" remote="129379350180000000" />
<file name="borderMiddleLeft.png" server="//192.168.1.2/wamp/www/busticketing/" local="129379350190066198" remote="129379350190000000" />
<file name="borderMiddleRight.png" server="//192.168.1.2/wamp/www/busticketing/" local="129379350190666233" remote="129379350190000000" />
<file name="borderTopCenter.png" server="//192.168.1.2/wamp/www/busticketing/" local="129379350191066256" remote="129379350190000000" />
<file name="borderTopLeft.png" server="//192.168.1.2/wamp/www/busticketing/" local="129379350191416276" remote="129379350190000000" />
<file name="borderTopRight.png" server="//192.168.1.2/wamp/www/busticketing/" local="129379350191606286" remote="129379350190000000" />
<file name="borderBottomCenter.png" server="C:/wamp/www/kiboslopes/" local="129379710200000000" remote="129379710200000000" />
<file name="borderBottomLeft.png" server="C:/wamp/www/kiboslopes/" local="129379710200000000" remote="129379710200000000" />
<file name="borderBottomRight.png" server="C:/wamp/www/kiboslopes/" local="129379710200000000" remote="129379710200000000" />
<file name="borderMiddleLeft.png" server="C:/wamp/www/kiboslopes/" local="129379710200000000" remote="129379710200000000" />
<file name="borderMiddleRight.png" server="C:/wamp/www/kiboslopes/" local="129379710200000000" remote="129379710200000000" />
<file name="borderTopCenter.png" server="C:/wamp/www/kiboslopes/" local="129379710200000000" remote="129379710200000000" />
<file name="borderTopLeft.png" server="C:/wamp/www/kiboslopes/" local="129379710200000000" remote="129379710200000000" />
<file name="borderTopRight.png" server="C:/wamp/www/kiboslopes/" local="129379710200000000" remote="129379710200000000" />
<file name="Thumbs.db" server="C:/wamp/www/kiboslopes/" local="129530620080000000" remote="129530620080000000" />
</dwsync>